README
ez_setup.py
setup.py
Rect.egg-info/PKG-INFO
Rect.egg-info/SOURCES.txt
Rect.egg-info/dependency_links.txt
Rect.egg-info/top_level.txt
rect/__init__.py
rect/hashmap.py
rect/packer.py
rect/quadtree.py
rect/rect.py
