Metadata-Version: 1.0
Name: Rect
Version: 5
Summary: A class for handling rectangle regions.
Home-page: http://code.google.com/p/corsair-redux/wiki/Rect
Author: Simon Wittber
Author-email: simonwittber@gmail.com
License: MIT
Platform: Any
